django_tsp/__init__.py
django_tsp/apis.py
django_tsp/apps.py
django_tsp/checks.py
django_tsp/conf.py
django_tsp/consumer.py
django_tsp/routing.py
django_tsp/serializers.py
django_tsp/services.py
django_tsp/views.py
django_tsp/management/commands/bridge.py
django_tsp/management/commands/reciver.py
django_tsp/management/commands/__pycache__/bridge.cpython-310.pyc
django_tsp/management/commands/__pycache__/reciver.cpython-310.pyc
django_tsp/templates/index.html
django_tsp-3.14.8.dist-info/LICENSE
django_tsp-3.14.8.dist-info/METADATA
django_tsp-3.14.8.dist-info/WHEEL
django_tsp-3.14.8.dist-info/top_level.txt
django_tsp-3.14.8.dist-info/RECORD
