Metadata-Version: 2.1
Name: django-tsp
Version: 3.14.8
Summary: django-tsp is a django travel salesman problem.
Home-page: https://github.com/TravelSalesmanProblem/django_tsp
Author: AmirBahador Bahadori
Author-email: amirbahador.pv@gmail.com
Maintainer: AmirBahador Bahadori
Maintainer-email: amirbahador.pv@gmail.com
License: MIT
Project-URL: Twitter, https://twitter.com/AmirBahadordev
Keywords: django,tsp
Classifier: Development Status :: 5 - Production/Stable
Classifier: Environment :: Web Environment
Classifier: Framework :: Django
Classifier: Framework :: Django :: 3.2
Classifier: Framework :: Django :: 4.0
Classifier: Framework :: Django :: 4.1
Classifier: Framework :: Django :: 4.2
Classifier: Intended Audience :: Developers
Classifier: License :: OSI Approved :: MIT License
Classifier: Natural Language :: English
Classifier: Operating System :: OS Independent
Classifier: Programming Language :: Python :: 3
Classifier: Programming Language :: Python :: 3 :: Only
Classifier: Programming Language :: Python :: 3.7
Classifier: Programming Language :: Python :: 3.8
Classifier: Programming Language :: Python :: 3.9
Classifier: Programming Language :: Python :: 3.10
Classifier: Programming Language :: Python :: 3.11
Classifier: Programming Language :: Python :: Implementation :: CPython
Classifier: Typing :: Typed
Requires-Python: >=3.7
License-File: LICENSE
Requires-Dist: Django (>=3.2)
Requires-Dist: tsp-wrapper (>=1.0.5)
